CHANGES.txt
CONTRIBUTORS.txt
MANIFEST.in
README.txt
setup.cfg
setup.py
docs/HISTORY.txt
docs/INSTALL.txt
docs/LICENSE.GPL
docs/LICENSE.txt
xhostplus/__init__.py
xhostplus.intropage.egg-info/PKG-INFO
xhostplus.intropage.egg-info/SOURCES.txt
xhostplus.intropage.egg-info/dependency_links.txt
xhostplus.intropage.egg-info/entry_points.txt
xhostplus.intropage.egg-info/namespace_packages.txt
xhostplus.intropage.egg-info/not-zip-safe
xhostplus.intropage.egg-info/paster_plugins.txt
xhostplus.intropage.egg-info/requires.txt
xhostplus.intropage.egg-info/top_level.txt
xhostplus/intropage/README.txt
xhostplus/intropage/__init__.py
xhostplus/intropage/config.py
xhostplus/intropage/configure.zcml
xhostplus/intropage/browser/__init__.py
xhostplus/intropage/browser/configure.zcml
xhostplus/intropage/browser/intropageview.pt
xhostplus/intropage/browser/intropageview.py
xhostplus/intropage/content/__init__.py
xhostplus/intropage/content/configure.zcml
xhostplus/intropage/content/intropage.py
xhostplus/intropage/interfaces/__init__.py
xhostplus/intropage/interfaces/intropage.py
xhostplus/intropage/locales/de/LC_MESSAGES/README.txt
xhostplus/intropage/locales/en/LC_MESSAGES/README.txt
xhostplus/intropage/portlets/__init__.py
xhostplus/intropage/portlets/configure.zcml
xhostplus/intropage/profiles/default/browserlayer.xml
xhostplus/intropage/profiles/default/factorytool.xml
xhostplus/intropage/profiles/default/metadata.xml
xhostplus/intropage/profiles/default/portlets.xml
xhostplus/intropage/profiles/default/rolemap.xml
xhostplus/intropage/profiles/default/types.xml
xhostplus/intropage/profiles/default/types/Intro_page.xml
xhostplus/intropage/tests/__init__.py
xhostplus/intropage/tests/base.py
xhostplus/intropage/tests/test_doctest.py