Metadata-Version: 1.0
Name: xhostplus.intropage
Version: 1.0.1
Summary: Intro page product for Plone 3/4
Home-page: http://www.xhostplus.at/
Author: Andreas Stocker
Author-email: andreas.stocker@xhostplus.at
License: GPL
Platform: UNKNOWN
Classifier: Framework :: Plone
Classifier: Intended Audience :: Developers
Classifier: License :: OSI Approved :: GNU General Public License (GPL)
